{
  "menu":{
    "about": "關於我們",
    "work": "遊戲",
    "gallery": "畫廊",
    "part": "合作夥伴",
    "contact": "聯絡我們"
  },
  "about":{
    "story": "赫米兔娛樂是一間來自台灣的獨立遊戲與故事創作團隊。<br/>我們以「故事」為核心，橫跨遊戲、漫畫、小說與各式互動媒介，<br/>創造出專屬的敘事宇宙。<br/>這裡，是一場從筆尖與光芒出發的冒險——<br/>歡迎來到我們的世界。"
  },
  "work":{
    "work101": "迷霧國度",
    "work102": " 一款融合劇情與策略的網頁<br/>卡牌RPG。玩家將在迷霧籠罩的<br/>艾諾爾大陸中，扮演英雄<br/>或怪物，構築牌組、養成技能，<br/>對抗迷霧之王的邪惡勢力。",
    "work103": " 在命運迷霧中，找回屬於你的真實。",
    "work201": "星際夥伴",
    "work202": "這是一場跨越星海的溫柔冒險，玩家將與小貓Hime與偵探Seeker展開星際旅程，在解謎與探索中找回記憶、理解情感。",
    "work203": "在銀河深處，總有一份情誼等你找回。",
    "work301": "摸摸茄",
    "work302": "一款介於搞怪與療癒之間的獨特「茄式蔬壓」遊戲。用愛意按壓茄子，體驗既病態又充滿情緒的互動過程。",
    "work303": "按下去的，是茄子，還是你的內心？",
    "work401": "迷霧國度：傳承",
    "work402": "一款策略戰棋與多結局角色扮演結合的史詩級RPG。玩家將在迷霧災難中周旋於各方勢力，寫下屬於自己家族的傳說。",
    "work403": "在霧與火的夾縫中，選擇你的忠誠與命運。",
    "work501": "追尋者聯盟",
    "work502": "運用區塊鏈技術的多人對戰集換式卡牌遊戲。三大陣營卡牌風格迥異，<br/>玩家將在賽季爭霸中集結卡片，爭奪成為世界的領主。",
    "work503": "集結你的聯盟，在卡牌與權力的棋盤中稱王。",
    "work601": "追尋者聯盟：英雄之旅",
    "work602": "以《追尋者聯盟》世界觀為背景的快節奏Roguelite卡牌RPG。<br/>選擇英雄組隊深入領主之島，逐步強化牌組並對抗強敵與命運。",
    "work603": "全新的冒險從你開始"
  },
  "contact":{
    "main": "無論你是創作者、出版商、開發團隊或品牌單位，<br/>我們都願意點亮那盞燈，和你一起開啟全新的冒險。"
  }
}